Sprezz/Sprezz.py
Sprezz/__init__.py
Sprezz/__main__.py
Sprezz-0.1.dist-info/LICENCE
Sprezz-0.1.dist-info/METADATA
Sprezz-0.1.dist-info/WHEEL
Sprezz-0.1.dist-info/entry_points.txt
Sprezz-0.1.dist-info/top_level.txt
Sprezz-0.1.dist-info/RECORD
