Metadata-Version: 2.1
Name: Sprezz
Version: 0.1
Summary: hello pypi :)
Home-page: https://github.com/ezzuldinSt/Spr-ezz
Author: Spr3z
Author-email: zezo.665.5@gmail.com
License: UNKNOWN
Platform: UNKNOWN
Classifier: Programming Language :: Python :: 3
Classifier: License :: OSI Approved :: MIT License
Classifier: Operating System :: OS Independent
